{
  "training.accuracy": {
    "steps": [
      0,
      1,
      2,
      3,
      4,
      5
    ],
    "timestamps": [
      "2019-04-13T06:15:22.359920",
      "2019-04-13T06:15:26.572321",
      "2019-04-13T06:15:28.267240",
      "2019-04-13T06:15:30.423935",
      "2019-04-13T06:15:33.299770",
      "2019-04-13T06:15:33.822738"
    ],
    "values": [
      2,
      4,
      6,
      8,
      10,
      12
    ]
  },
  "training.diff": {
    "steps": [
      0,
      1,
      2,
      3,
      4,
      5
    ],
    "timestamps": [
      "2019-04-13T06:15:22.360007",
      "2019-04-13T06:15:26.572338",
      "2019-04-13T06:15:28.267294",
      "2019-04-13T06:15:30.423952",
      "2019-04-13T06:15:33.299823",
      "2019-04-13T06:15:33.822755"
    ],
    "values": [
      2,
      4,
      6,
      8,
      10,
      12
    ]
  },
  "training.loss": {
    "steps": [
      2,
      4,
      6
    ],
    "timestamps": [
      "2019-04-13T06:15:26.572270",
      "2019-04-13T06:15:30.423883",
      "2019-04-13T06:15:33.822684"
    ],
    "values": [
      3.0,
      6.0,
      9.0
    ]
  }
}